setup.py
rl4uc/__init__.py
rl4uc/data_retrieval.py
rl4uc/dispatch.py
rl4uc/environment.py
rl4uc_pwdemars.egg-info/PKG-INFO
rl4uc_pwdemars.egg-info/SOURCES.txt
rl4uc_pwdemars.egg-info/dependency_links.txt
rl4uc_pwdemars.egg-info/top_level.txt