Metadata-Version: 2.1
Name: rl4uc-pwdemars
Version: 0.0.1
Summary: Reinforcement learning environment for the unit commitment problem
Home-page: UNKNOWN
Author: Patrick de Mars
Author-email: pwdemars@gmail.com
License: UNKNOWN
Platform: UNKNOWN
Classifier: Programming Language :: Python :: 3
Classifier: License :: OSI Approved :: MIT License
Classifier: Operating System :: OS Independent
Requires-Python: >=3.6
